postalsend/__init__.py
postalsend/_app.py
postalsend/authentication.py
postalsend/errors.py
postalsend/message.py
postalsend/push.py
postalsend-0.1.1.dist-info/LICENSE
postalsend-0.1.1.dist-info/METADATA
postalsend-0.1.1.dist-info/WHEEL
postalsend-0.1.1.dist-info/top_level.txt
postalsend-0.1.1.dist-info/RECORD
