Metadata-Version: 2.2
Name: postalsend
Version: 0.1.1
Summary: A library to send messages with the Postal server API.
Home-page: https://github.com/steelproxy/postal-sender-lib
Author: Collin Rodes
Author-email: steelproxy@protonmail.com
Classifier: Programming Language :: Python :: 3
Classifier: License :: OSI Approved :: MIT License
Classifier: Operating System :: OS Independent
Requires-Python: >=3.6
License-File: LICENSE
Requires-Dist: requests>=2.31.0
Dynamic: author
Dynamic: author-email
Dynamic: classifier
Dynamic: description
Dynamic: description-content-type
Dynamic: home-page
Dynamic: requires-dist
Dynamic: requires-python
Dynamic: summary
